{"commonName": "", "firstName": "Gheorghe", "headshotImgUrl": "https://fifa17.content.easports.com/fifa/fltOnlineAssets/B1BA185F-AD7C-4128-8A64-746DE4EC5A82/2018/fut/items/images/players/html5/134x134/166124.png", "lastName": "Hagi", "league": {"abbrName": "ICN", "id": 2118, "imgUrl": null, "name": "Icons"}, "nation": {"imageUrls": {"small": "https://fifa17.content.easports.com/fifa/fltOnlineAssets/B1BA185F-AD7C-4128-8A64-746DE4EC5A82/2018/fut/items/images/flags/html5/24x14/39.png", "medium": "https://fifa17.content.easports.com/fifa/fltOnlineAssets/B1BA185F-AD7C-4128-8A64-746DE4EC5A82/2018/fut/items/images/flags/html5/30x19/39.png", "large": "https://fifa17.content.easports.com/fifa/fltOnlineAssets/B1BA185F-AD7C-4128-8A64-746DE4EC5A82/2018/fut/items/images/flags/html5/40x25/39.png"}, "abbrName": "Romania", "id": 39, "imgUrl": null, "name": "Romania"}, "club": {"imageUrls": {"dark": {"small": "https://fifa17.content.easports.com/fifa/fltOnlineAssets/B1BA185F-AD7C-4128-8A64-746DE4EC5A82/2018/fut/items/images/clubbadges/html5/dark/24x24/l112658.png", "medium": "https://fifa17.content.easports.com/fifa/fltOnlineAssets/B1BA185F-AD7C-4128-8A64-746DE4EC5A82/2018/fut/items/images/clubbadges/html5/dark/27x27/l112658.png", "large": "https://fifa17.content.easports.com/fifa/fltOnlineAssets/B1BA185F-AD7C-4128-8A64-746DE4EC5A82/2018/fut/items/images/clubbadges/html5/dark/34x34/l112658.png"}, "normal": {"small": "https://fifa17.content.easports.com/fifa/fltOnlineAssets/B1BA185F-AD7C-4128-8A64-746DE4EC5A82/2018/fut/items/images/clubbadges/html5/normal/24x24/l112658.png", "medium": "https://fifa17.content.easports.com/fifa/fltOnlineAssets/B1BA185F-AD7C-4128-8A64-746DE4EC5A82/2018/fut/items/images/clubbadges/html5/normal/27x27/l112658.png", "large": "https://fifa17.content.easports.com/fifa/fltOnlineAssets/B1BA185F-AD7C-4128-8A64-746DE4EC5A82/2018/fut/items/images/clubbadges/html5/normal/34x34/l112658.png"}}, "abbrName": "Icons", "id": 112658, "imgUrl": null, "name": "Icons"}, "headshot": {"largeImgUrl": "https://fifa17.content.easports.com/fifa/fltOnlineAssets/B1BA185F-AD7C-4128-8A64-746DE4EC5A82/2018/fut/items/images/players/html5/134x134/166124.png", "medImgUrl": "https://fifa17.content.easports.com/fifa/fltOnlineAssets/B1BA185F-AD7C-4128-8A64-746DE4EC5A82/2018/fut/items/images/players/html5/105x105/166124.png", "smallImgUrl": "https://fifa17.content.easports.com/fifa/fltOnlineAssets/B1BA185F-AD7C-4128-8A64-746DE4EC5A82/2018/fut/items/images/players/html5/40x40/166124.png"}, "specialImages": {"largeTOTWImgUrl": null, "medTOTWImgUrl": null}, "position": "CAM", "composure": 89, "playStyle": "Basic", "playStyleId": null, "height": 172, "weight": 68, "birthdate": "1965-02-05", "age": 53, "acceleration": 84, "aggression": 61, "agility": 86, "balance": 84, "ballcontrol": 92, "foot": "Left", "skillMoves": 4, "crossing": 89, "curve": 88, "dribbling": 90, "finishing": 85, "freekickaccuracy": 94, "gkdiving": 11, "gkhandling": 15, "gkkicking": 12, "gkpositioning": 6, "gkreflexes": 7, "headingaccuracy": 58, "interceptions": 44, "jumping": 74, "longpassing": 88, "longshots": 92, "marking": 34, "penalties": 91, "positioning": 88, "potential": 91, "reactions": 88, "shortpassing": 92, "shotpower": 93, "slidingtackle": 41, "sprintspeed": 83, "standingtackle": 46, "stamina": 78, "strength": 60, "vision": 89, "volleys": 88, "weakFoot": 4, "traits": ["Flair", "Shooting - Long Shot Taker", "Playmaker", "Shooting - Chip Shot", "Corner Specialist", "Takes Finesse Style Free Kicks"], "specialities": ["Dribbler", "Play Maker", "Distance Shooter", "Crosser", "FK Specialist", "Acrobat", "Midfielder"], "atkWorkRate": "Medium", "defWorkRate": "Low", "playerType": "Icon", "attributes": [{"name": "fut.attribute.PAC", "value": 83, "chemistryBonus": [0]}, {"name": "fut.attribute.SHO", "value": 89, "chemistryBonus": [0]}, {"name": "fut.attribute.PAS", "value": 90, "chemistryBonus": [0]}, {"name": "fut.attribute.DRI", "value": 90, "chemistryBonus": [0]}, {"name": "fut.attribute.DEF", "value": 43, "chemistryBonus": [0]}, {"name": "fut.attribute.PHY", "value": 65, "chemistryBonus": [0]}], "name": "Hagi", "quality": "gold", "color": "legend", "isGK": false, "positionFull": "Centre Attacking Midfielder", "isSpecialType": true, "contracts": null, "fitness": null, "rawAttributeChemistryBonus": null, "isLoan": null, "squadPosition": null, "iconAttributes": {"clubTeamStats": [{"years": 1, "clubId": 110075, "clubName": "Farul Constan\u021ba", "appearances": 18, "goals": 7}, {"years": 4, "clubId": 110754, "clubName": "Sportul Studentesc", "appearances": 107, "goals": 58}, {"years": 3, "clubId": 100761, "clubName": "Steaua Bucaresti", "appearances": 97, "goals": 76}, {"years": 2, "clubId": 243, "clubName": "Real Madrid", "appearances": 84, "goals": 20}, {"years": 2, "clubId": 190, "clubName": "Brescia", "appearances": 61, "goals": 15}, {"years": 2, "clubId": 241, "clubName": "FC Barcelona", "appearances": 51, "goals": 11}, {"years": 5, "clubId": 325, "clubName": "Galatasaray SK", "appearances": 175, "goals": 70}], "nationalTeamStats": [{"years": 17, "clubId": 1356, "clubName": "Romania", "appearances": 124, "goals": 35}], "iconText": "Gheorghe Hagi\u2019s final club was Turkish giants Galatasaray. In his four-year spell, Hagi collected many honours, scoring 73 goals and making 26 assists. He helped them win the Turkish league title each season, the Turkish Cup twice, a UEFA Cup and a UEFA Super Cup, which came against former club Real Madrid. At the age of 35, in his last major tournament, Romania made the UEFA Euro 2000 quarter-finals. He remains the joint leading goal scorer for Romania."}, "itemType": "player", "discardValue": null, "id": "166124", "modelName": "FUTPlayerItem", "baseId": 166124, "rating": 91}